deteksigempaterkini/__init__.py
dataterkinigempabumidiindoensia-0.1.dist-info/LICENSE
dataterkinigempabumidiindoensia-0.1.dist-info/METADATA
dataterkinigempabumidiindoensia-0.1.dist-info/WHEEL
dataterkinigempabumidiindoensia-0.1.dist-info/top_level.txt
dataterkinigempabumidiindoensia-0.1.dist-info/RECORD
